slither/__init__.py
slither/__main__.py
slither/config.py
slither/core/board.py
slither/core/food.py
slither/core/game.py
slither/core/gamestate.py
slither/core/score_manager.py
slither/core/skin_manager.py
slither/core/snake.py
slither/skins/__init__.py
slither/skins/classic.py
slither/skins/fire.py
slither/skins/forest.py
slither/skins/halloween.py
slither/skins/ice.py
slither/skins/matrix.py
slither/skins/monochrome.py
slither/skins/ocean.py
slither/skins/pastel.py
slither/skins/solarized.py
slither/skins/sunset.py
slither/skins/synthwave.py
slither/ui/renderer.py
slither/ui/sound.py
slither_py-1.0.0.dist-info/LICENSE
slither_py-1.0.0.dist-info/METADATA
slither_py-1.0.0.dist-info/WHEEL
slither_py-1.0.0.dist-info/entry_points.txt
slither_py-1.0.0.dist-info/RECORD
