Metadata-Version: 2.3
Name: slither-py
Version: 1.0.0
Summary: A modern and stylish Snake game built with Python and Pygame, featuring a synthwave aesthetic.
License: MIT
Keywords: snake,game,pygame,retro,synthwave
Author: vmaritato
Author-email: v.maritato@icloud.com
Requires-Python: >=3.10,<4.0
Classifier: Development Status :: 4 - Beta
Classifier: Environment :: MacOS X
Classifier: Intended Audience :: End Users/Desktop
Classifier: License :: OSI Approved :: MIT License
Classifier: Programming Language :: Python :: 3
Classifier: Programming Language :: Python :: 3.10
Classifier: Programming Language :: Python :: 3.11
Classifier: Programming Language :: Python :: 3.12
Classifier: Programming Language :: Python :: 3.13
Classifier: Topic :: Games/Entertainment :: Arcade
Requires-Dist: pygame (>=2.6.0,<3.0.0)
Requires-Dist: typer[rich] (>=0.9.0,<0.10.0)
Project-URL: Homepage, https://github.com/vmaritato/slither-py
Project-URL: Repository, https://github.com/vmaritato/slither-py
